daglite_rich/__init__.py
daglite_rich/logging.json
daglite_rich/logging.py
daglite_rich/progress.py
daglite_rich/py.typed
daglite_rich-0.3.0.dist-info/METADATA
daglite_rich-0.3.0.dist-info/WHEEL
daglite_rich-0.3.0.dist-info/top_level.txt
daglite_rich-0.3.0.dist-info/RECORD
