Metadata-Version: 2.4
Name: daglite-rich
Version: 0.3.0
Summary: Rich logging and progress bars for daglite.
Requires-Dist: daglite
Requires-Dist: rich
